magicka/__init__.py
magicka/_core/errors.py
magicka/_core/lexer.py
magicka/_core/rules.py
magicka/_core/tokens.py
magicka/_test/__init__.py
magicka/_test/lexer.py
magicka-0.1.0.dist-info/LICENSE.md
magicka-0.1.0.dist-info/WHEEL
magicka-0.1.0.dist-info/METADATA
magicka-0.1.0.dist-info/RECORD
