Metadata-Version: 2.1
Name: magicka
Version: 0.1.0
Summary: Web automation, made magical
Author: IgnisDa
Author-email: ignisda2002@gmail.com
Requires-Python: >=3.6,<4.0
Classifier: Programming Language :: Python :: 3
Classifier: Programming Language :: Python :: 3.6
Classifier: Programming Language :: Python :: 3.7
Classifier: Programming Language :: Python :: 3.8
Classifier: Programming Language :: Python :: 3.9
Requires-Dist: ply (>=3.11,<4.0)
